Metadata-Version: 1.0
Name: sim-dist-test707
Version: 0.1
Summary: Binomial distribution
Home-page: UNKNOWN
Author: UNKNOWN
Author-email: UNKNOWN
License: UNKNOWN
Platform: UNKNOWN
